tiny_thingy.py
Tiny_Thingy-1.0.0.dist-info/METADATA
Tiny_Thingy-1.0.0.dist-info/RECORD
Tiny_Thingy-1.0.0.dist-info/WHEEL
Tiny_Thingy-1.0.0.dist-info/top_level.txt
