Metadata-Version: 2.1
Name: Tiny-Thingy
Version: 1.0.0
Summary: JSON database with python object notation
Home-page: https://github.com/Shir0kamii/tiny-thingy
Author: Shir0kamii
Author-email: UNKNOWN
License: MIT
Platform: any
Classifier: Intended Audience :: Developers
Classifier: Operating System :: OS Independent
Classifier: Programming Language :: Python
Classifier: Topic :: Database
Classifier: Topic :: Software Development :: Libraries :: Python Modules
Requires-Dist: thingy (>=0.8.3)
Requires-Dist: tinydb (>=3.9.0)
